{"post_title":"Finance calculator","post_content":"<!-- wp:jet-forms\/number-field {\"value\":{\"groups\":[]},\"min\":\"500\",\"max\":\"30000\",\"step\":\"1\",\"label\":\"Enter the amount you wish to finance\",\"name\":\"amount\",\"default\":\"1000\",\"required\":true} \/-->\n\n<!-- wp:jet-forms\/radio-field {\"field_options\":[{\"label\":\"6\",\"value\":\"6\",\"calculate\":\"6\",\"__visible\":true},{\"label\":\"12\",\"value\":\"12\",\"calculate\":\"12\"},{\"label\":\"24\",\"value\":\"24\",\"calculate\":\"24\"},{\"label\":\"36\",\"value\":\"36\",\"calculate\":\"36\"},{\"label\":\"48\",\"value\":\"48\",\"calculate\":\"48\"},{\"label\":\"60\",\"value\":\"60\",\"calculate\":\"60\"}],\"label\":\"Select the number of monthly payments\",\"name\":\"months\",\"default\":\"6\"} \/-->\n\n<!-- wp:columns -->\n<div class=\"wp-block-columns\"><!-- wp:column -->\n<div class=\"wp-block-column\"><!-- wp:jet-forms\/calculated-field {\"value_type\":\"string\",\"calc_formula\":\"\\u0022%months%\\u0022 == \\u00226\\u0022 ? 0 : \\u0022%months%\\u0022 == \\u002212\\u0022 ? 0 : 9.9\",\"calc_suffix\":\"%\"} \/-->\n\n<!-- wp:jet-forms\/calculated-field {\"value_type\":\"string\",\"calc_formula\":\"\\u0022%months%\\u0022 == \\u00226\\u0022 ? %amount%\/%months% : \\u0022%months%\\u0022 == \\u002212\\u0022 ? %amount%\/%months% : \\u0022%months%\\u0022==\\u002224\\u0022 ? (%amount% * 0.046071) :\\u0022%months%\\u0022==\\u002236\\u0022 ? (%amount% * 0.031969): \\u0022%months%\\u0022==\\u002248\\u0022? (%amount% * 0.025571):\\u0022%months%\\u0022==\\u002260\\u0022? (%amount% * 0.021241):0\",\"calc_prefix\":\"£\",\"calc_suffix\":\"\\u0026nbsp;per month\",\"calc_hidden\":true,\"name\":\"monthly_cost_calc\"} \/-->\n\n<!-- wp:jet-forms\/calculated-field {\"calc_formula\":\"%monthly_cost_calc%\",\"label\":\"Per Month\",\"name\":\"per_month_pay\"} \/-->\n\n<!-- wp:jet-forms\/calculated-field {\"calc_formula\":\"%total_to_pay_back%-%amount%\",\"calc_prefix\":\"£\",\"label\":\"Cost of Credit\",\"name\":\"cost_of_credit\"} \/-->\n\n<!-- wp:jet-forms\/calculated-field {\"calc_formula\":\"%monthly_cost_calc%*%months%\",\"calc_prefix\":\"£\",\"label\":\"Total To Pay Back\",\"name\":\"total_to_pay_back\"} \/--><\/div>\n<!-- \/wp:column --><\/div>\n<!-- \/wp:columns -->","meta_input":{"_jf_actions":"[{\"id\":2849,\"settings\":{},\"type\":\"save_record\",\"conditions\":[],\"events\":[],\"chosen\":false,\"selected\":false}]","footnotes":""}}