{"content":[{"id":"26ee2e8c","settings":{"flex_direction":"column","content_width":"full","min_height":{"unit":"em","size":"","sizes":[]},"min_height_tablet":{"unit":"em","size":"","sizes":[]},"min_height_mobile":{"unit":"em","size":"","sizes":[]},"overflow":"hidden","custom_css":"selector:hover .hover-img {\n    transform: scale(1.1);\n}\n\n.hover-img {\n    transform: scale(1.01);\n    transition: transform .4s ease;\n}\n\nselector:hover .slide-anim {\n    padding-bottom: 1em;\n    opacity: 1;\n}\n\n.slide-anim {\n    opacity: 0;\n    padding-bottom: 0;\n    transition: all .4s ease;\n}\n\nselector:hover .slide-adjuster {\n    padding-bottom: 0;\n}\n\n.slide-adjuster {\n    padding-bottom: 1em;\n    transition: all .4s ease;\n}\n\nselector:hover .show-on-hover {\n    opacity: 1;\n}\n\n.show-on-hover {\n    opacity: 0;\n    transition: opacity .4s ease;\n}\n\nselector:hover .hover-gradient {\n    transform: translateY(-10%);\n    opacity: 1;\n}\n\n.hover-gradient {\n    transform: translateY(10%);\n    opacity: 0;\n    transition: all 0.4s ease;\n}","__dynamic__":[]},"elements":[{"id":"ed93d9f","settings":{"content_width":"full","min_height":{"unit":"custom","size":"100%","sizes":[]},"min_height_tablet":{"unit":"em","size":"","sizes":[]},"min_height_mobile":{"unit":"em","size":"","sizes":[]},"flex_direction":"column","flex_justify_content":"flex-start","flex_align_items":"flex-start","background_position":"center center","background_repeat":"no-repeat","background_size":"cover","padding":{"unit":"em","top":"1","right":"1","bottom":"1","left":"1","isLinked":true},"padding_tablet":{"unit":"em","top":"","right":"","bottom":"","left":"","isLinked":true},"padding_mobile":{"unit":"em","top":"1","right":"1","bottom":"1","left":"1","isLinked":true},"__dynamic__":{"background_image":"[elementor-tag id=\"4053b0d\" name=\"jet-post-custom-image\" settings=\"%7B%22img_field%22%3A%22presse-feature-image%22%7D\"]"},"overflow":"hidden","background_hover_position":"center center","background_hover_repeat":"no-repeat","background_hover_size":"initial","background_hover_bg_width":{"unit":"%","size":110,"sizes":[]},"background_background":"classic","position":"absolute","css_classes":"hover-img","_title":"Image"},"elements":[],"isInner":true,"elType":"container"},{"id":"c5ecd2","settings":{"content_width":"full","min_height":{"unit":"custom","size":"120%","sizes":[]},"min_height_tablet":{"unit":"em","size":"","sizes":[]},"min_height_mobile":{"unit":"em","size":"","sizes":[]},"flex_direction":"column","flex_justify_content":"flex-start","flex_align_items":"flex-start","background_position":"center center","background_repeat":"no-repeat","background_size":"cover","padding":{"unit":"em","top":"1","right":"1","bottom":"1","left":"1","isLinked":true},"padding_tablet":{"unit":"em","top":"","right":"","bottom":"","left":"","isLinked":true},"padding_mobile":{"unit":"em","top":"1","right":"1","bottom":"1","left":"1","isLinked":true},"__dynamic__":{"link":"[elementor-tag id=\"c4f94ee\" name=\"post-url\" settings=\"%7B%7D\"]","background_image":"[elementor-tag id=\"4053b0d\" name=\"jet-post-custom-image\" settings=\"%7B%22img_field%22%3A%22presse-feature-image%22%7D\"]"},"overflow":"hidden","html_tag":"a","background_hover_position":"center center","background_hover_repeat":"no-repeat","background_hover_size":"initial","background_hover_bg_width":{"unit":"%","size":110,"sizes":[]},"background_background":"gradient","background_color":"#FFFFFF00","background_color_b":"#2980B9","position":"absolute","css_classes":"hover-gradient","_title":"Slider Gradient","__globals__":{"background_color":"","background_color_b":"globals\/colors?id=eb690a2"}},"elements":[],"isInner":true,"elType":"container"},{"id":"7532fc50","settings":{"content_width":"full","min_height":{"unit":"custom","size":"100%","sizes":[]},"min_height_tablet":{"unit":"custom","size":"","sizes":[]},"min_height_mobile":{"unit":"custom","size":"","sizes":[]},"flex_direction":"column","flex_justify_content":"space-between","flex_gap":{"column":"3","row":"3","isLinked":true,"unit":"em","size":3},"flex_gap_tablet":{"column":"","row":"","isLinked":true,"unit":"em","size":null},"flex_gap_mobile":{"column":"","row":"","isLinked":true,"unit":"em","size":null},"padding":{"unit":"em","top":"1.5","right":"1.5","bottom":"1.5","left":"1.5","isLinked":true},"padding_tablet":{"unit":"em","top":"","right":"","bottom":"","left":"","isLinked":true},"padding_mobile":{"unit":"em","top":"","right":"","bottom":"","left":"","isLinked":true},"_title":"Content","__dynamic__":[]},"elements":[{"id":"4a3a25da","settings":{"content_width":"full","flex_align_items":"flex-end","_title":"Top"},"elements":[{"id":"663a5354","settings":{"selected_icon":{"value":"fas fa-arrow-right","library":"fa-solid"},"view":"stacked","size":{"unit":"em","size":1,"sizes":[]},"size_tablet":{"unit":"em","size":"","sizes":[]},"size_mobile":{"unit":"em","size":"","sizes":[]},"_css_classes":"show-on-hover","__globals__":{"primary_color":"globals\/colors?id=eb690a2"}},"elements":[],"isInner":false,"widgetType":"icon","elType":"widget"}],"isInner":true,"elType":"container"},{"id":"62645f8f","settings":{"content_width":"full","_title":"Bottom"},"elements":[{"id":"6f5155a3","settings":{"content_width":"full","css_classes":"slide-adjuster"},"elements":[{"id":"3b0eedb5","settings":{"space":{"unit":"px","size":0,"sizes":[]}},"elements":[],"isInner":false,"widgetType":"spacer","elType":"widget"}],"isInner":true,"elType":"container"},{"id":"151646e7","settings":{"content_width":"full","css_classes":"slide-anim","_title":"Slider"},"elements":[{"id":"6fc86402","settings":{"title":"blandit massa","header_size":"p","typography_typography":"custom","typography_font_family":"Manrope","typography_font_size":{"unit":"em","size":0.585,"sizes":[]},"typography_font_size_tablet":{"unit":"em","size":"","sizes":[]},"typography_font_size_mobile":{"unit":"em","size":"","sizes":[]},"typography_font_weight":"700","typography_text_transform":"uppercase","typography_line_height":{"unit":"em","size":1,"sizes":[]},"typography_letter_spacing":{"unit":"em","size":0.02,"sizes":[]},"typography_letter_spacing_tablet":{"unit":"em","size":"","sizes":[]},"typography_letter_spacing_mobile":{"unit":"em","size":"","sizes":[]},"__globals__":{"title_color":"globals\/colors?id=4a22635"},"typography_word_spacing":{"unit":"em","size":"","sizes":[]},"_background_color_stop_tablet":{"unit":"%","size":"","sizes":[]},"_background_color_stop_mobile":{"unit":"%","size":"","sizes":[]},"_background_color_b_stop_tablet":{"unit":"%","size":"","sizes":[]},"_background_color_b_stop_mobile":{"unit":"%","size":"","sizes":[]},"_background_gradient_angle_tablet":{"unit":"deg","size":"","sizes":[]},"_background_gradient_angle_mobile":{"unit":"deg","size":"","sizes":[]},"_background_gradient_position_tablet":"center center","_background_gradient_position_mobile":"center center","_background_hover_color_stop_tablet":{"unit":"%","size":"","sizes":[]},"_background_hover_color_stop_mobile":{"unit":"%","size":"","sizes":[]},"_background_hover_color_b_stop_tablet":{"unit":"%","size":"","sizes":[]},"_background_hover_color_b_stop_mobile":{"unit":"%","size":"","sizes":[]},"_background_hover_gradient_angle_tablet":{"unit":"deg","size":"","sizes":[]},"_background_hover_gradient_angle_mobile":{"unit":"deg","size":"","sizes":[]},"_background_hover_gradient_position_tablet":"center center","_background_hover_gradient_position_mobile":"center center","__dynamic__":{"title":"[elementor-tag id=\"75d9c8d\" name=\"jet-term-field\" settings=\"%7B%22taxonomy%22%3A%22presse-categories%22%2C%22term_field%22%3A%22name%22%7D\"]","link":"[elementor-tag id=\"15b19c1\" name=\"jet-term-field\" settings=\"%7B%22taxonomy%22%3A%22presse-categories%22%2C%22term_field%22%3A%22term_url%22%7D\"]"}},"elements":[],"isInner":false,"widgetType":"heading","elType":"widget"},{"id":"27db8392","settings":{"title":"fringilla est ullamcorper ","typography_typography":"custom","typography_font_family":"Manrope","typography_font_size":{"unit":"em","size":1,"sizes":[]},"typography_font_size_tablet":{"unit":"em","size":"","sizes":[]},"typography_font_size_mobile":{"unit":"em","size":"","sizes":[]},"typography_font_weight":"700","typography_text_transform":"capitalize","typography_line_height":{"unit":"em","size":1.25,"sizes":[]},"__globals__":{"title_color":"globals\/colors?id=4a22635"},"header_size":"h3","typography_word_spacing":{"unit":"em","size":"","sizes":[]},"_background_color_stop_tablet":{"unit":"%","size":"","sizes":[]},"_background_color_stop_mobile":{"unit":"%","size":"","sizes":[]},"_background_color_b_stop_tablet":{"unit":"%","size":"","sizes":[]},"_background_color_b_stop_mobile":{"unit":"%","size":"","sizes":[]},"_background_gradient_angle_tablet":{"unit":"deg","size":"","sizes":[]},"_background_gradient_angle_mobile":{"unit":"deg","size":"","sizes":[]},"_background_gradient_position_tablet":"center center","_background_gradient_position_mobile":"center center","_background_hover_color_stop_tablet":{"unit":"%","size":"","sizes":[]},"_background_hover_color_stop_mobile":{"unit":"%","size":"","sizes":[]},"_background_hover_color_b_stop_tablet":{"unit":"%","size":"","sizes":[]},"_background_hover_color_b_stop_mobile":{"unit":"%","size":"","sizes":[]},"_background_hover_gradient_angle_tablet":{"unit":"deg","size":"","sizes":[]},"_background_hover_gradient_angle_mobile":{"unit":"deg","size":"","sizes":[]},"_background_hover_gradient_position_tablet":"center center","_background_hover_gradient_position_mobile":"center center","__dynamic__":{"title":"[elementor-tag id=\"0e40664\" name=\"post-title\" settings=\"%7B%7D\"]","link":"[elementor-tag id=\"093fa55\" name=\"post-url\" settings=\"%7B%7D\"]"}},"elements":[],"isInner":false,"widgetType":"heading","elType":"widget"}],"isInner":true,"elType":"container"}],"isInner":true,"elType":"container"}],"isInner":true,"elType":"container"},{"id":"7afb7680","settings":{"content_width":"full","min_height":{"unit":"custom","size":"100%","sizes":[]},"min_height_tablet":{"unit":"em","size":"","sizes":[]},"min_height_mobile":{"unit":"em","size":"","sizes":[]},"flex_direction":"column","flex_justify_content":"flex-start","flex_align_items":"flex-start","background_position":"center center","background_repeat":"no-repeat","background_size":"cover","padding":{"unit":"em","top":"1","right":"1","bottom":"1","left":"1","isLinked":true},"padding_tablet":{"unit":"em","top":"","right":"","bottom":"","left":"","isLinked":true},"padding_mobile":{"unit":"em","top":"1","right":"1","bottom":"1","left":"1","isLinked":true},"__dynamic__":{"link":"[elementor-tag id=\"c4f94ee\" name=\"post-url\" settings=\"%7B%7D\"]"},"overflow":"hidden","html_tag":"a","background_hover_position":"center center","background_hover_repeat":"no-repeat","background_hover_size":"initial","background_hover_bg_width":{"unit":"%","size":110,"sizes":[]},"position":"absolute","css_classes":"hover-img","_title":"Click"},"elements":[],"isInner":true,"elType":"container"}],"isInner":false,"elType":"container"}],"page_settings":{"listing_post_type":"presse","listing_tax":"category","preview_width":{"unit":"px","size":300,"sizes":[]}},"version":"0.4","title":"slide-up-hover-img-grad","type":"container"}